{
  "overall_sentiment_distribution": {
    "positive": 10,
    "neutral": 2,
    "negative": 8
  },
  "dominant_emotions": [
    "joy",
    "anger",
    "sarcasm"
  ],
  "toxic_comment_count": 5,
  "controversy_score": 0.85,
  "key_topics": [
    "nationalism",
    "boycott movements",
    "religious and ethnic tensions"
  ],
  "frequent_bias_or_group_mentions": [
    "India",
    "Pakistan",
    "Turkey",
    "Muslims",
    "Arabs"
  ],
  "sarcasm_detected": true,
  "languages_detected": [
    "English",
    "Turkish",
    "Urdu"
  ],
  "spam_comment_count": 0,
  "summary": "The comment section is highly polarized with a strong presence of nationalistic sentiments, particularly involving India, Pakistan, and Turkey. There's a notable use of sarcasm and joy, alongside expressions of anger and toxicity. The discussions revolve around boycott movements, religious and ethnic tensions, with a significant amount of controversy and polarization.",
  "title": "India Boycotts, Turkey Laughs 😂",
  "uploader_id": "@smiletojannah"
}